mcp_business_central/__init__.py
mcp_business_central/__main__.py
mcp_business_central/server.py
mcp_business_central/api/__init__.py
mcp_business_central/api/companies.py
mcp_business_central/api/config.py
mcp_business_central/api/entities.py
mcp_business_central/api/http_client.py
mcp_business_central/api/odata/__init__.py
mcp_business_central/api/odata/metadata.py
mcp_business_central/auth/__init__.py
mcp_business_central/auth/manager.py
mcp_business_central/logging/__init__.py
mcp_business_central/logging/exceptions.py
mcp_business_central/tools/__init__.py
mcp_business_central/tools/mcp_tools.py
mcp_business_central/utils/__init__.py
mcp_business_central-1.0.10.dist-info/licenses/LICENSE
mcp_business_central-1.0.10.dist-info/METADATA
mcp_business_central-1.0.10.dist-info/WHEEL
mcp_business_central-1.0.10.dist-info/entry_points.txt
mcp_business_central-1.0.10.dist-info/top_level.txt
mcp_business_central-1.0.10.dist-info/RECORD
