Metadata-Version: 2.4
Name: mcp-business-central
Version: 1.0.10
Summary: MCP Server for Microsoft Dynamics 365 Business Central
Author-email: Dmitry Katson <dmitry@katson.com>
License-Expression: MIT
Project-URL: Homepage, https://github.com/DmitryKatson/mcp-business-central
Project-URL: Repository, https://github.com/DmitryKatson/mcp-business-central
Project-URL: Issues, https://github.com/DmitryKatson/mcp-business-central/issues
Project-URL: Documentation, https://github.com/DmitryKatson/mcp-business-central#readme
Classifier: Programming Language :: Python :: 3
Classifier: Programming Language :: Python :: 3.10
Requires-Python: >=3.10
License-File: LICENSE
Requires-Dist: fastmcp>=2.0.0
Requires-Dist: requests>=2.28.0
Requires-Dist: python-dotenv>=1.0.0
Requires-Dist: msal>=1.24.0
Requires-Dist: aiohttp>=3.9.0
Dynamic: license-file
